<annotation><filename>2169121853</filename><size><width>150</width><height>113</height><depth>3</depth></size><object><name>11</name><truncated>0</truncated><difficult>0</difficult><bndbox><xmin>4</xmin><ymin>6</ymin><xmax>145</xmax><ymax>102</ymax></bndbox></object><object><name>11</name><truncated>0</truncated><difficult>0</difficult><bndbox><xmin>4</xmin><ymin>6</ymin><xmax>145</xmax><ymax>102</ymax></bndbox></object><object><name>11</name><truncated>0</truncated><difficult>0</difficult><bndbox><xmin>4</xmin><ymin>6</ymin><xmax>145</xmax><ymax>102</ymax></bndbox></object><object><name>11</name><truncated>0</truncated><difficult>0</difficult><bndbox><xmin>4</xmin><ymin>6</ymin><xmax>145</xmax><ymax>102</ymax></bndbox></object></annotation>