<annotation><filename>4027042513</filename><size><width>375</width><height>500</height><depth>3</depth></size><object><name>21</name><truncated>0</truncated><difficult>0</difficult><bndbox><xmin>149</xmin><ymin>199</ymin><xmax>250</xmax><ymax>247</ymax></bndbox></object><object><name>21</name><truncated>0</truncated><difficult>0</difficult><bndbox><xmin>149</xmin><ymin>199</ymin><xmax>250</xmax><ymax>247</ymax></bndbox></object><object><name>21</name><truncated>0</truncated><difficult>0</difficult><bndbox><xmin>149</xmin><ymin>199</ymin><xmax>250</xmax><ymax>247</ymax></bndbox></object></annotation>