<annotation><filename>788959598</filename><size><width>375</width><height>500</height><depth>3</depth></size><object><name>8</name><truncated>0</truncated><difficult>0</difficult><bndbox><xmin>118</xmin><ymin>255</ymin><xmax>260</xmax><ymax>407</ymax></bndbox></object><object><name>8</name><truncated>0</truncated><difficult>0</difficult><bndbox><xmin>118</xmin><ymin>255</ymin><xmax>260</xmax><ymax>407</ymax></bndbox></object><object><name>8</name><truncated>0</truncated><difficult>0</difficult><bndbox><xmin>118</xmin><ymin>255</ymin><xmax>260</xmax><ymax>407</ymax></bndbox></object><object><name>8</name><truncated>0</truncated><difficult>0</difficult><bndbox><xmin>118</xmin><ymin>255</ymin><xmax>260</xmax><ymax>407</ymax></bndbox></object></annotation>